LICENSE
MANIFEST.in
README.md
setup.py
tap_chargebee/__init__.py
tap_chargebee/client.py
tap_chargebee/state.py
tap_chargebee.egg-info/PKG-INFO
tap_chargebee.egg-info/SOURCES.txt
tap_chargebee.egg-info/dependency_links.txt
tap_chargebee.egg-info/entry_points.txt
tap_chargebee.egg-info/requires.txt
tap_chargebee.egg-info/top_level.txt
tap_chargebee/schemas/common/cards.json
tap_chargebee/schemas/common/comments.json
tap_chargebee/schemas/common/credit_notes.json
tap_chargebee/schemas/common/customers.json
tap_chargebee/schemas/common/gifts.json
tap_chargebee/schemas/common/invoices.json
tap_chargebee/schemas/common/orders.json
tap_chargebee/schemas/common/payment_sources.json
tap_chargebee/schemas/common/promotional_credits.json
tap_chargebee/schemas/common/quotes.json
tap_chargebee/schemas/common/transactions.json
tap_chargebee/schemas/common/virtual_bank_accounts.json
tap_chargebee/schemas/item_model/coupons.json
tap_chargebee/schemas/item_model/events.json
tap_chargebee/schemas/item_model/item_families.json
tap_chargebee/schemas/item_model/item_prices.json
tap_chargebee/schemas/item_model/items.json
tap_chargebee/schemas/item_model/subscriptions.json
tap_chargebee/schemas/plan_model/addons.json
tap_chargebee/schemas/plan_model/coupons.json
tap_chargebee/schemas/plan_model/events.json
tap_chargebee/schemas/plan_model/plans.json
tap_chargebee/schemas/plan_model/subscriptions.json
tap_chargebee/streams/__init__.py
tap_chargebee/streams/addons.py
tap_chargebee/streams/base.py
tap_chargebee/streams/comments.py
tap_chargebee/streams/coupons.py
tap_chargebee/streams/credit_notes.py
tap_chargebee/streams/customers.py
tap_chargebee/streams/events.py
tap_chargebee/streams/gifts.py
tap_chargebee/streams/invoices.py
tap_chargebee/streams/item_families.py
tap_chargebee/streams/item_prices.py
tap_chargebee/streams/items.py
tap_chargebee/streams/orders.py
tap_chargebee/streams/payment_sources.py
tap_chargebee/streams/plans.py
tap_chargebee/streams/promotional_credits.py
tap_chargebee/streams/quotes.py
tap_chargebee/streams/subscriptions.py
tap_chargebee/streams/transactions.py
tap_chargebee/streams/util.py
tap_chargebee/streams/virtual_bank_accounts.py
tests/test_chargebee_all_fields.py
