Metadata-Version: 1.1
Name: tap-chargebee
Version: 1.4.0
Summary: Singer.io tap for extracting data from the Chargebee API
Home-page: UNKNOWN
Author: dwallace@envoy.com
Author-email: UNKNOWN
License: UNKNOWN
Platform: UNKNOWN
Classifier: Programming Language :: Python :: 3 :: Only
